setup.py
collective/__init__.py
collective.simpleeditbutton.egg-info/PKG-INFO
collective.simpleeditbutton.egg-info/SOURCES.txt
collective.simpleeditbutton.egg-info/dependency_links.txt
collective.simpleeditbutton.egg-info/entry_points.txt
collective.simpleeditbutton.egg-info/namespace_packages.txt
collective.simpleeditbutton.egg-info/not-zip-safe
collective.simpleeditbutton.egg-info/requires.txt
collective.simpleeditbutton.egg-info/top_level.txt
collective/simpleeditbutton/README.txt
collective/simpleeditbutton/__init__.py
collective/simpleeditbutton/configure.zcml
collective/simpleeditbutton/interfaces.py
collective/simpleeditbutton/simpleeditbutton.pt
collective/simpleeditbutton/viewlets.py
collective/simpleeditbutton/profiles/default/browserlayer.xml
collective/simpleeditbutton/profiles/default/metadata.xml
collective/simpleeditbutton/profiles/default/rolemap.xml
collective/simpleeditbutton/tests/__init__.py
collective/simpleeditbutton/tests/base.py
collective/simpleeditbutton/tests/test_doctest.py
docs/HISTORY.txt
docs/INSTALL.txt
docs/LICENSE.GPL
docs/LICENSE.txt