Metadata-Version: 1.0
Name: collective.simpleeditbutton
Version: 1.0
Summary: Adjusts the default permissions so that users with the Member role only see an edit button for items they are allowed to modify, rather than the full set of tabs and actions
Home-page: http://svn.plone.org/svn/collective/collective.simpleeditbutton
Author: David Glick
Author-email: davidglick@onenw.org
License: GPL
Keywords: plone member edit
Platform: UNKNOWN
Classifier: Framework :: Plone
Classifier: Intended Audience :: Developers
Classifier: Topic :: Software Development :: Libraries :: Python Modules
Classifier: License :: OSI Approved :: GNU General Public License (GPL)
